setup.py
pgpbfunniest/__init__.py
pgpbfunniest.egg-info/PKG-INFO
pgpbfunniest.egg-info/SOURCES.txt
pgpbfunniest.egg-info/dependency_links.txt
pgpbfunniest.egg-info/not-zip-safe
pgpbfunniest.egg-info/top_level.txt